Lab 3/mux2to1/mux2to1.v
module mux2to1 (w0,w1,s,f);
	input w0,w1,s;
	output f;
	reg f;
	always @(w0 or w1 or s)
	f = s?w1:w0;
endmodule

Lab 3/mux2to1/mux2to1_tb.v
`timescale 1ns/1ns
`include "mux2to1.v"
module mux2to1_tb();
reg x1,x2,s;
wire f;
integer i;
mux2to1 func(x1,x2,s,f);
initial
begin
	$dumpfile("mux2to1_tb.vcd");
	$dumpvars(0,mux2to1_tb);
	for(i=0;i<8;i=i+1) begin
		{s,x1,x2} = i;#20;
	end
	$display("test complete");
end
endmodule

Lab 3/mux2to1/mux2to1_tb.vcd
$date
	Wed Aug 14 09:44:29 2024
$end
$version
	Icarus Verilog
$end
$timescale
	1ns
$end
$scope module mux2to1_tb $end
$var wire 1 ! f $end
$var reg 1 " s $end
$var reg 1 # x1 $end
$var reg 1 $ x2 $end
$var integer 32 % i [31:0] $end
$scope module func $end
$var wire 1 " s $end
$var wire 1 # w0 $end
$var wire 1 $ w1 $end
$var reg 1 ! f $end
$upscope $end
$upscope $end
$enddefinitions $end
#0
$dumpvars
b0 %
0$
0#
0"
0!
$end
#20
1$
b1 %
#40
1!
1#
0$
b10 %
#60
1$
b11 %
#80
0!
1"
0#
0$
b100 %
#100
1!
1$
b101 %
#120
0!
1#
0$
b110 %
#140
1!
1$
b111 %
#160
b1000 %
