Lab 1/1b/Lab1b.v
module Lab1b(a,b,c,d,f);
	input a, b, c, d;
	output f;
	assign f = (~a&~d)|(b&~d)|(c&~d)|(~a&b&c);
endmodule

Lab 1/1b/Lab1b_tb.v
`timescale 1ns/1ns
`include "Lab1b.v"

module Lab1b_tb();
reg a, b, c, d;
wire f;
integer i;
Lab1b func(a, b, c, d, f);
initial
begin
	$dumpfile("Lab1b_tb.vcd");
	$dumpvars(0,Lab1b_tb);
	for(i=0;i<16;i=i+1) begin
		{a, b, c, d} = i;#20;
	end
	$display("Test complete");
end
endmodule

Lab 1/1b/Lab1b_tb.vcd
$date
	Mon Aug  5 19:48:17 2024
$end
$version
	Icarus Verilog
$end
$timescale
	1ns
$end
$scope module Lab1b_tb $end
$var wire 1 ! f $end
$var reg 1 " a $end
$var reg 1 # b $end
$var reg 1 $ c $end
$var reg 1 % d $end
$var integer 32 & i [31:0] $end
$scope module func $end
$var wire 1 " a $end
$var wire 1 # b $end
$var wire 1 $ c $end
$var wire 1 % d $end
$var wire 1 ! f $end
$upscope $end
$upscope $end
$enddefinitions $end
$comment Show the parameter values. $end
$dumpall
$end
#0
$dumpvars
b0 &
0%
0$
0#
0"
1!
$end
#20
0!
1%
b1 &
#40
1!
1$
0%
b10 &
#60
0!
1%
b11 &
#80
1!
1#
0$
0%
b100 &
#100
0!
1%
b101 &
#120
1!
1$
0%
b110 &
#140
1%
b111 &
#160
0!
1"
0#
0$
0%
b1000 &
#180
1%
b1001 &
#200
1!
1$
0%
b1010 &
#220
0!
1%
b1011 &
#240
1!
1#
0$
0%
b1100 &
#260
0!
1%
b1101 &
#280
1!
1$
0%
b1110 &
#300
0!
1%
b1111 &
#320
b10000 &
