Lab 2/1/Q1.v
module Q1(a,b,c,d,f);
	input a,b,c,d;
	output f;
	assign g = a&b;
	assign h = c|d;
	assign f = ~(g^h);
endmodule

Lab 2/1/Q1_tb.v
`timescale 1ns/1ns
`include "Q1.v"
module Q1_tb();
reg a,b,c,d;
wire f;
integer i;
Q1 func(a,b,c,d,f);
initial
begin
	$dumpfile("Q1_tb.vcd");
	$dumpvars(0,Q1_tb);
	for(i=0;i<16;i=i+1) begin
		{a,b,c,d} = i;#20;
	end
	$display("Test complete");
end
endmodule

Lab 2/1/Q1_tb.vcd
$date
	Wed Aug  7 09:39:05 2024
$end
$version
	Icarus Verilog
$end
$timescale
	1ns
$end
$scope module Q1_tb $end
$var wire 1 ! f $end
$var reg 1 " a $end
$var reg 1 # b $end
$var reg 1 $ c $end
$var reg 1 % d $end
$var integer 32 & i [31:0] $end
$scope module func $end
$var wire 1 " a $end
$var wire 1 # b $end
$var wire 1 $ c $end
$var wire 1 % d $end
$var wire 1 ! f $end
$var wire 1 ' g $end
$var wire 1 ( h $end
$upscope $end
$upscope $end
$enddefinitions $end
#0
$dumpvars
0(
0'
b0 &
0%
0$
0#
0"
1!
$end
#20
0!
1(
1%
b1 &
#40
1$
0%
b10 &
#60
1%
b11 &
#80
1!
0(
1#
0$
0%
b100 &
#100
0!
1(
1%
b101 &
#120
1$
0%
b110 &
#140
1%
b111 &
#160
1!
0(
1"
0#
0$
0%
b1000 &
#180
0!
1(
1%
b1001 &
#200
1$
0%
b1010 &
#220
1%
b1011 &
#240
1'
0(
1#
0$
0%
b1100 &
#260
1!
1(
1%
b1101 &
#280
1$
0%
b1110 &
#300
1%
b1111 &
#320
b10000 &
