Lab 4/Solved ex/Solved.v
module Solved(W, Y, En);
	input [1:0] W;
	input En;
	output [0:3] Y;
	reg [0:3] Y;
	integer k;
	always @(W or En)
		for (k = 0; k <= 3; k = k+1)
			if ((W == k) && (En == 1))
				Y[k] = 1;
			else
				Y[k] = 0;
endmodule

Lab 4/Solved ex/Solved_tb.v
`timescale 1ns/1ns
`include "Solved.v"
module Solved_tb();
	reg [1:0]w;
	reg En;
	wire [0:3]f;
	integer i;
	Solved func(w,f,En);
	initial
	begin
		$dumpfile("Solved_tb.vcd");
		$dumpvars(0,Solved_tb);
		for(i=0;i<8;i++) begin
			{En,w} = i;#20;
		end
		$display("test complete");
	end
endmodule

Lab 4/Solved ex/Solved_tb.vcd
$date
	Wed Aug 21 09:46:57 2024
$end
$version
	Icarus Verilog
$end
$timescale
	1ns
$end
$scope module Solved_tb $end
$var wire 4 ! f [0:3] $end
$var reg 1 " En $end
$var reg 2 # w [1:0] $end
$var integer 32 $ i [31:0] $end
$scope module func $end
$var wire 1 " En $end
$var wire 2 % W [1:0] $end
$var reg 4 & Y [0:3] $end
$var integer 32 ' k [31:0] $end
$upscope $end
$upscope $end
$enddefinitions $end
#0
$dumpvars
b100 '
b0 &
b0 %
b0 $
b0 #
0"
b0 !
$end
#20
b100 '
b1 #
b1 %
b1 $
#40
b100 '
b10 #
b10 %
b10 $
#60
b100 '
b11 #
b11 %
b11 $
#80
b1000 !
b1000 &
b100 '
1"
b0 #
b0 %
b100 $
#100
b100 !
b100 &
b100 '
b1 #
b1 %
b101 $
#120
b10 !
b10 &
b100 '
b10 #
b10 %
b110 $
#140
b1 !
b1 &
b100 '
b11 #
b11 %
b111 $
#160
b1000 $
