Lab 2/2/Q2.v
module Q2(a,b,ci,co,s);
	input a,b,ci;
	output co,s;
	assign co = (a&b)|(a&ci)|(b&ci);
	assign s = a^b^ci;
endmodule

Lab 2/2/Q2_tb.v
`timescale 1ns/1ns
`include "Q2.v"
module Q2_tb();
reg a,b,ci;
wire co,s;
integer i;
Q2 func(a,b,ci,co,s);
initial
begin
	$dumpfile("Q2_tb.vcd");
	$dumpvars(0,Q2_tb);
	for(i=0;i<8;i=i+1) begin
		{a,b,ci} = i;#20;
	end
	$display("Test complete");
end
endmodule

Lab 2/2/Q2_tb.vcd
$date
	Wed Aug  7 10:06:25 2024
$end
$version
	Icarus Verilog
$end
$timescale
	1ns
$end
$scope module Q2_tb $end
$var wire 1 ! s $end
$var wire 1 " co $end
$var reg 1 # a $end
$var reg 1 $ b $end
$var reg 1 % ci $end
$var integer 32 & i [31:0] $end
$scope module func $end
$var wire 1 # a $end
$var wire 1 $ b $end
$var wire 1 % ci $end
$var wire 1 " co $end
$var wire 1 ! s $end
$upscope $end
$upscope $end
$enddefinitions $end
#0
$dumpvars
b0 &
0%
0$
0#
0"
0!
$end
#20
1!
1%
b1 &
#40
1!
1$
0%
b10 &
#60
1"
0!
1%
b11 &
#80
0"
1!
1#
0$
0%
b100 &
#100
1"
0!
1%
b101 &
#120
0!
1$
0%
b110 &
#140
1!
1%
b111 &
#160
b1000 &
