Lab 4/Q2/dec2to4.v
module dec2to4(W, Y, En);
	input [1:0] W;
	input En;
	output reg [3:0] Y;
	integer k;
	always @(W or En)
		for (k = 0; k <= 3; k = k+1)
			if ((W == k) && (En == 1))
				Y[k] = 1;
			else
				Y[k] = 0;
endmodule

Lab 4/Q2/Q2.v
`include "dec2to4.v"
module Q2(
    input [3:0] W,
    input En,
    output [15:0] Y,
    output [3:0] x
    );
	wire [3:0] x;
	integer k;
	dec2to4 func(
	    .W(W[3:2]),
	    .Y(x),
	    .En(En)
	);
	dec2to4 d3(
        .W(W[1:0]),
        .Y(Y[15:12]),
        .En(x[3])
    );
	dec2to4 d2(
        .W(W[1:0]),
        .Y(Y[11:8]),
        .En(x[2])
    );
    dec2to4 d1(
        .W(W[1:0]),
        .Y(Y[7:4]),
        .En(x[1])
    );
    dec2to4 d0(
        .W(W[1:0]),
        .Y(Y[3:0]),
        .En(x[0])
    );
endmodule

Lab 4/Q2/Q2_tb.v
`timescale 1ns/1ns
`include "Q2.v"
module Q2_tb();
	reg [3:0]w;
	reg En;
	wire [15:0]f;
	wire [3:0]x;
	integer i;
	Q2 func(w,En,f,x);
	initial
	begin
		$dumpfile("Q2_tb.vcd");
		$dumpvars(0,Q2_tb);
		for(i=0;i<32;i=i+1) begin
			{En,w} = i;#10;
		end
		$display("test complete");
	end
endmodule

Lab 4/Q2/Q2_tb.vcd
$date
	Wed Aug 21 11:21:48 2024
$end
$version
	Icarus Verilog
$end
$timescale
	1ns
$end
$scope module Q2_tb $end
$var wire 4 ! x [3:0] $end
$var wire 16 " f [15:0] $end
$var reg 1 # En $end
$var reg 4 $ w [3:0] $end
$var integer 32 % i [31:0] $end
$scope module func $end
$var wire 1 # En $end
$var wire 4 & W [3:0] $end
$var wire 4 ' x [3:0] $end
$var wire 16 ( Y [15:0] $end
$scope module d0 $end
$var wire 1 ) En $end
$var wire 2 * W [1:0] $end
$var reg 4 + Y [3:0] $end
$var integer 32 , k [31:0] $end
$upscope $end
$scope module d1 $end
$var wire 1 - En $end
$var wire 2 . W [1:0] $end
$var reg 4 / Y [3:0] $end
$var integer 32 0 k [31:0] $end
$upscope $end
$scope module d2 $end
$var wire 1 1 En $end
$var wire 2 2 W [1:0] $end
$var reg 4 3 Y [3:0] $end
$var integer 32 4 k [31:0] $end
$upscope $end
$scope module d3 $end
$var wire 1 5 En $end
$var wire 2 6 W [1:0] $end
$var reg 4 7 Y [3:0] $end
$var integer 32 8 k [31:0] $end
$upscope $end
$scope module func $end
$var wire 1 # En $end
$var wire 2 9 W [1:0] $end
$var reg 4 : Y [3:0] $end
$var integer 32 ; k [31:0] $end
$upscope $end
$upscope $end
$upscope $end
$enddefinitions $end
#0
$dumpvars
b100 ;
b0 :
b0 9
b100 8
b0 7
b0 6
05
b100 4
b0 3
b0 2
01
b100 0
b0 /
b0 .
0-
b100 ,
b0 +
b0 *
0)
b0 (
b0 '
b0 &
b0 %
b0 $
0#
b0 "
b0 !
$end
#10
b100 8
b100 4
b100 0
b100 ,
b1 6
b1 2
b1 .
b1 *
b1 $
b1 &
b1 %
#20
b100 8
b100 4
b100 0
b100 ,
b10 6
b10 2
b10 .
b10 *
b10 $
b10 &
b10 %
#30
b100 8
b100 4
b100 0
b100 ,
b11 6
b11 2
b11 .
b11 *
b11 $
b11 &
b11 %
#40
b100 ;
b100 8
b100 4
b100 0
b100 ,
b1 9
b0 6
b0 2
b0 .
b0 *
b100 $
b100 &
b100 %
#50
b100 8
b100 4
b100 0
b100 ,
b1 6
b1 2
b1 .
b1 *
b101 $
b101 &
b101 %
#60
b100 8
b100 4
b100 0
b100 ,
b10 6
b10 2
b10 .
b10 *
b110 $
b110 &
b110 %
#70
b100 8
b100 4
b100 0
b100 ,
b11 6
b11 2
b11 .
b11 *
b111 $
b111 &
b111 %
#80
b100 ;
b100 8
b100 4
b100 0
b100 ,
b10 9
b0 6
b0 2
b0 .
b0 *
b1000 $
b1000 &
b1000 %
#90
b100 8
b100 4
b100 0
b100 ,
b1 6
b1 2
b1 .
b1 *
b1001 $
b1001 &
b1001 %
#100
b100 8
b100 4
b100 0
b100 ,
b10 6
b10 2
b10 .
b10 *
b1010 $
b1010 &
b1010 %
#110
b100 8
b100 4
b100 0
b100 ,
b11 6
b11 2
b11 .
b11 *
b1011 $
b1011 &
b1011 %
#120
b100 ;
b100 8
b100 4
b100 0
b100 ,
b11 9
b0 6
b0 2
b0 .
b0 *
b1100 $
b1100 &
b1100 %
#130
b100 8
b100 4
b100 0
b100 ,
b1 6
b1 2
b1 .
b1 *
b1101 $
b1101 &
b1101 %
#140
b100 8
b100 4
b100 0
b100 ,
b10 6
b10 2
b10 .
b10 *
b1110 $
b1110 &
b1110 %
#150
b100 8
b100 4
b100 0
b100 ,
b11 6
b11 2
b11 .
b11 *
b1111 $
b1111 &
b1111 %
#160
b1 "
b1 (
b1 +
1)
b100 8
b100 4
b100 0
b100 ,
b1 !
b1 '
b1 :
b100 ;
b0 9
b0 6
b0 2
b0 .
b0 *
1#
b0 $
b0 &
b10000 %
#170
b100 8
b100 4
b100 0
b10 "
b10 (
b10 +
b100 ,
b1 6
b1 2
b1 .
b1 *
b1 $
b1 &
b10001 %
#180
b100 8
b100 4
b100 0
b100 "
b100 (
b100 +
b100 ,
b10 6
b10 2
b10 .
b10 *
b10 $
b10 &
b10010 %
#190
b100 8
b100 4
b100 0
b1000 "
b1000 (
b1000 +
b100 ,
b11 6
b11 2
b11 .
b11 *
b11 $
b11 &
b10011 %
#200
b1 /
1-
0)
b10 !
b10 '
b10 :
b100 ;
b100 8
b100 4
b100 0
b10000 "
b10000 (
b0 +
b100 ,
b1 9
b0 6
b0 2
b0 .
b0 *
b100 $
b100 &
b10100 %
#210
b100 8
b100 4
b100000 "
b100000 (
b10 /
b100 0
b100 ,
b1 6
b1 2
b1 .
b1 *
b101 $
b101 &
b10101 %
#220
b100 8
b100 4
b1000000 "
b1000000 (
b100 /
b100 0
b100 ,
b10 6
b10 2
b10 .
b10 *
b110 $
b110 &
b10110 %
#230
b100 8
b100 4
b10000000 "
b10000000 (
b1000 /
b100 0
b100 ,
b11 6
b11 2
b11 .
b11 *
b111 $
b111 &
b10111 %
#240
b1 3
11
0-
b100 !
b100 '
b100 :
b100 ;
b100 8
b100 4
b100000000 "
b100000000 (
b0 /
b100 0
b100 ,
b10 9
b0 6
b0 2
b0 .
b0 *
b1000 $
b1000 &
b11000 %
#250
b100 8
b1000000000 "
b1000000000 (
b10 3
b100 4
b100 0
b100 ,
b1 6
b1 2
b1 .
b1 *
b1001 $
b1001 &
b11001 %
#260
b100 8
b10000000000 "
b10000000000 (
b100 3
b100 4
b100 0
b100 ,
b10 6
b10 2
b10 .
b10 *
b1010 $
b1010 &
b11010 %
#270
b100 8
b100000000000 "
b100000000000 (
b1000 3
b100 4
b100 0
b100 ,
b11 6
b11 2
b11 .
b11 *
b1011 $
b1011 &
b11011 %
#280
b1 7
15
01
b1000 !
b1000 '
b1000 :
b100 ;
b100 8
b1000000000000 "
b1000000000000 (
b0 3
b100 4
b100 0
b100 ,
b11 9
b0 6
b0 2
b0 .
b0 *
b1100 $
b1100 &
b11100 %
#290
b10000000000000 "
b10000000000000 (
b10 7
b100 8
b100 4
b100 0
b100 ,
b1 6
b1 2
b1 .
b1 *
b1101 $
b1101 &
b11101 %
#300
b100000000000000 "
b100000000000000 (
b100 7
b100 8
b100 4
b100 0
b100 ,
b10 6
b10 2
b10 .
b10 *
b1110 $
b1110 &
b11110 %
#310
b1000000000000000 "
b1000000000000000 (
b1000 7
b100 8
b100 4
b100 0
b100 ,
b11 6
b11 2
b11 .
b11 *
b1111 $
b1111 &
b11111 %
#320
b100000 %
