Lab 4/Q3/Q3.v
module Q3(
    input  [3:0] in,
    output reg [1:0] out,
    output reg valid
);
    always @(*) begin
        valid = 1'b1;
        casex (in)
            4'b1xxx: out = 2'b11;
            4'b01xx: out = 2'b10;
            4'b001x: out = 2'b01;
            4'b0001: out = 2'b00;
            4'b0000: begin
                out = 2'bxx;
                valid = 1'b0;
            end
            default: begin
                out = 2'bxx;
                valid = 1'b0;
            end
        endcase
    end
endmodule

Lab 4/Q3/Q3_tb.v
`timescale 1ns/1ns
`include "Q3.v"
module Q3_tb();
    reg [3:0]in;
    wire [1:0]out;
    wire valid;
    integer i;
    Q3 func(in, out, valid);
    initial
    begin
        $dumpfile("Q3_tb.vcd");
        $dumpvars(0, Q3_tb);
        for (i = 0; i < 16; i = i + 1) begin
            in = i; #10;
        end
        $display("Test complete");
    end
endmodule

Lab 4/Q3/Q3_tb.vcd
$date
	Tue Aug 27 16:40:49 2024
$end
$version
	Icarus Verilog
$end
$timescale
	1ns
$end
$scope module Q3_tb $end
$var wire 1 ! valid $end
$var wire 2 " out [1:0] $end
$var reg 4 # in [3:0] $end
$var integer 32 $ i [31:0] $end
$scope module func $end
$var wire 4 % in [3:0] $end
$var reg 2 & out [1:0] $end
$var reg 1 ! valid $end
$upscope $end
$upscope $end
$enddefinitions $end
$comment Show the parameter values. $end
$dumpall
$end
#0
$dumpvars
bx &
b0 %
b0 $
b0 #
bx "
0!
$end
#10
b0 "
b0 &
1!
b1 #
b1 %
b1 $
#20
b1 "
b1 &
b10 #
b10 %
b10 $
#30
b11 #
b11 %
b11 $
#40
b10 "
b10 &
b100 #
b100 %
b100 $
#50
b101 #
b101 %
b101 $
#60
b110 #
b110 %
b110 $
#70
b111 #
b111 %
b111 $
#80
b11 "
b11 &
b1000 #
b1000 %
b1000 $
#90
b1001 #
b1001 %
b1001 $
#100
b1010 #
b1010 %
b1010 $
#110
b1011 #
b1011 %
b1011 $
#120
b1100 #
b1100 %
b1100 $
#130
b1101 #
b1101 %
b1101 $
#140
b1110 #
b1110 %
b1110 $
#150
b1111 #
b1111 %
b1111 $
#160
b10000 $
