Lab 1/A2/LabA2.v
module LabA2(x1,x2,x3,x4,f);
	input x1, x2, x3, x4;
	output f;
	assign f = (x2&x3&x4)|(x1&x2&x3)|(x1&x3&x4)|(x1&x2&x4);
endmodule

Lab 1/A2/LabA2_tb.v
`timescale 1ns/1ns
`include "LabA2.v"

module LabA2_tb();
reg x1, x2, x3, x4;
wire f;
integer i;
LabA2 func(x1,x2,x3,x4,f);
initial
begin
	$dumpfile("LabA2_tb.vcd");
	$dumpvars(0,LabA2_tb);
	for(i=0;i<16;i=i+1) begin
		{x1, x2, x3, x4} = i;#20;
	end
	$display("Test complete");
end
endmodule

Lab 1/A2/LabA2_tb.vcd
$date
	Wed Aug  7 00:40:58 2024
$end
$version
	Icarus Verilog
$end
$timescale
	1ns
$end
$scope module LabA2_tb $end
$var wire 1 ! f $end
$var reg 1 " x1 $end
$var reg 1 # x2 $end
$var reg 1 $ x3 $end
$var reg 1 % x4 $end
$var integer 32 & i [31:0] $end
$scope module func $end
$var wire 1 ! f $end
$var wire 1 " x1 $end
$var wire 1 # x2 $end
$var wire 1 $ x3 $end
$var wire 1 % x4 $end
$upscope $end
$upscope $end
$enddefinitions $end
$comment Show the parameter values. $end
$dumpall
$end
#0
$dumpvars
b0 &
0%
0$
0#
0"
0!
$end
#20
1%
b1 &
#40
1$
0%
b10 &
#60
1%
b11 &
#80
1#
0$
0%
b100 &
#100
1%
b101 &
#120
1$
0%
b110 &
#140
1!
1%
b111 &
#160
0!
1"
0#
0$
0%
b1000 &
#180
1%
b1001 &
#200
1$
0%
b1010 &
#220
1!
1%
b1011 &
#240
0!
1#
0$
0%
b1100 &
#260
1!
1%
b1101 &
#280
1!
1$
0%
b1110 &
#300
1%
b1111 &
#320
b10000 &
