Lab 1/2a/Lab2a.v
module Lab2a(a,b,c,d,f);
	input a, b, c, d;
	output f;
	assign f = (c|d)&(b+c)&(~a+~b+~c+~d);
endmodule

Lab 1/2a/Lab2a_tb.v
`timescale 1ns/1ns
`include "Lab2a.v"

module Lab2a_tb();
reg a, b, c, d;
wire f;
integer i;
Lab2a func(a, b, c, d, f);
initial
begin
	$dumpfile("Lab2a_tb.vcd");
	$dumpvars(0,Lab2a_tb);
	for(i=0;i<16;i=i+1) begin
		{a, b, c, d} = i;#20;
	end
	$display("Test complete");
end
endmodule

Lab 1/2a/Lab2a_tb.vcd
$date
	Tue Aug  6 14:42:53 2024
$end
$version
	Icarus Verilog
$end
$timescale
	1ns
$end
$scope module Lab2a_tb $end
$var wire 1 ! f $end
$var reg 1 " a $end
$var reg 1 # b $end
$var reg 1 $ c $end
$var reg 1 % d $end
$var integer 32 & i [31:0] $end
$scope module func $end
$var wire 1 " a $end
$var wire 1 # b $end
$var wire 1 $ c $end
$var wire 1 % d $end
$var wire 1 ! f $end
$upscope $end
$upscope $end
$enddefinitions $end
$comment Show the parameter values. $end
$dumpall
$end
#0
$dumpvars
b0 &
0%
0$
0#
0"
0!
$end
#20
1%
b1 &
#40
1!
1$
0%
b10 &
#60
0!
1%
b11 &
#80
1#
0$
0%
b100 &
#100
1%
b101 &
#120
1$
0%
b110 &
#140
1%
b111 &
#160
1"
0#
0$
0%
b1000 &
#180
1%
b1001 &
#200
1$
0%
b1010 &
#220
1!
1%
b1011 &
#240
0!
1#
0$
0%
b1100 &
#260
1!
1%
b1101 &
#280
0!
1$
0%
b1110 &
#300
1%
b1111 &
#320
b10000 &
