Lab 2/A2/QA2.v
module QA2(a,b,ci,co,s,land,lnand,lnor,lor,lxor,lxnor);
	input a,b,ci;
	output co,s,land,lnand,lnor,lor,lxor,lxnor;
	assign co = (a&b)|(a&ci)|(b&ci);
	assign s = a^b^ci;
	assign land = co&(~(ci^s));
	assign lnand = ~(co&(~(ci^s)));
	assign lnor = ~co&(~(ci^s));
	assign lor = co|(ci^s);
	assign lxor = (~ci&s)|(ci&~s);
	assign lxnor = ~((~ci&s)|(ci&~s));
endmodule

Lab 2/A2/QA2_tb.v
`timescale 1ns/1ns
`include "QA2.v"
module QA2_tb();
reg a,b,ci;
wire co,s,land,lnand,lnor,lor,lxor,lxnor;
integer i;
QA2 func(a,b,ci,co,s,land,lnand,lnor,lor,lxor,lxnor);
initial
begin
	$dumpfile("QA2_tb.vcd");
	$dumpvars(0,QA2_tb);
	for(i=0;i<8;i=i+1) begin
		{a,b,ci} = i;#10;
	end
	$display("Test complete");
end
endmodule

Lab 2/A2/QA2_tb.vcd
$date
	Wed Aug  7 11:02:03 2024
$end
$version
	Icarus Verilog
$end
$timescale
	1ns
$end
$scope module QA2_tb $end
$var wire 1 ! s $end
$var wire 1 " lxor $end
$var wire 1 # lxnor $end
$var wire 1 $ lor $end
$var wire 1 % lnor $end
$var wire 1 & lnand $end
$var wire 1 ' land $end
$var wire 1 ( co $end
$var reg 1 ) a $end
$var reg 1 * b $end
$var reg 1 + ci $end
$var integer 32 , i [31:0] $end
$scope module func $end
$var wire 1 ) a $end
$var wire 1 * b $end
$var wire 1 + ci $end
$var wire 1 ( co $end
$var wire 1 ' land $end
$var wire 1 & lnand $end
$var wire 1 % lnor $end
$var wire 1 $ lor $end
$var wire 1 # lxnor $end
$var wire 1 " lxor $end
$var wire 1 ! s $end
$upscope $end
$upscope $end
$enddefinitions $end
#0
$dumpvars
b0 ,
0+
0*
0)
0(
0'
1&
1%
0$
1#
0"
0!
$end
#10
1%
1#
0$
0"
1!
1+
b1 ,
#20
0#
1"
0%
1$
1!
1*
0+
b10 ,
#30
1&
0#
0'
0%
1"
1(
1$
0!
1+
b11 ,
#40
0#
0(
1"
1!
1)
0*
0+
b100 ,
#50
0#
1(
0%
1"
1$
0!
1+
b101 ,
#60
0&
1'
1#
0"
0!
1*
0+
b110 ,
#70
0&
1'
1#
0"
1!
1+
b111 ,
#80
b1000 ,
