Lab 4/Q1/Q1.v
module Q1(W, Y, En);
	input [1:0] W;
	input En;
	output reg [3:0] Y;
	integer k;
	always @(W or En)
		for (k = 0; k <= 3; k = k+1)
			if ((W == k) && (En == 0))
				Y[k] = 1;
			else
				Y[k] = 0;
endmodule

Lab 4/Q1/Q1_tb.v
`timescale 1ns/1ns
`include "Q1.v"
module Q1_tb();
	reg [1:0]w;
	reg En;
	wire [3:0]f;
	integer i;
	Q1 func(w,f,En);
	initial
	begin
		$dumpfile("Q1_tb.vcd");
		$dumpvars(0,Q1_tb);
		for(i=0;i<8;i++) begin
			{En,w} = i;#20;
		end
		$display("test complete");
	end
endmodule

Lab 4/Q1/Q1_tb.vcd
$date
	Wed Aug 21 11:20:26 2024
$end
$version
	Icarus Verilog
$end
$timescale
	1ns
$end
$scope module Q1_tb $end
$var wire 4 ! f [3:0] $end
$var reg 1 " En $end
$var reg 2 # w [1:0] $end
$var integer 32 $ i [31:0] $end
$scope module func $end
$var wire 1 " En $end
$var wire 2 % W [1:0] $end
$var reg 4 & Y [3:0] $end
$var integer 32 ' k [31:0] $end
$upscope $end
$upscope $end
$enddefinitions $end
#0
$dumpvars
b100 '
b1 &
b0 %
b0 $
b0 #
0"
b1 !
$end
#20
b10 !
b10 &
b100 '
b1 #
b1 %
b1 $
#40
b100 !
b100 &
b100 '
b10 #
b10 %
b10 $
#60
b1000 !
b1000 &
b100 '
b11 #
b11 %
b11 $
#80
b0 !
b0 &
b100 '
1"
b0 #
b0 %
b100 $
#100
b100 '
b1 #
b1 %
b101 $
#120
b100 '
b10 #
b10 %
b110 $
#140
b100 '
b11 #
b11 %
b111 $
#160
b1000 $
