Lab 5/Q1/Q1.v
module Q1(A,B,C,D,i,s0,s1,f);
	input A,B,C,D;
	output s0,s1;
	output reg [3:0]i;
	output reg f;
	assign s1 = A;
	assign s0 = B;	
	always @(*) begin
		i[0] = ~(C&D);
		i[1] = ~D;
		i[2] = ~C&D;
		i[3] = ~D;
		if(s1==0 && s0==0) begin
			f = i[0]; end
		else if(s1==0 && s0==1) begin
			f = i[1]; end
		else if(s1==1 && s0==0) begin
			f = i[2]; end
		else if(s1==1 && s0==1) begin
			f = i[3]; end
	end
endmodule

Lab 5/Q1/Q1_tb.v
`include "Q1.v"
`timescale 1ns/1ns
module Q1_tb();
	reg A,B,C,D;
	wire [3:0] i;
	wire s0,s1,f;
	integer k;
	Q1 func(A,B,C,D,i,s0,s1,f);
	initial
	begin
		$dumpfile("Q1_tb.vcd");
		$dumpvars(0,Q1_tb);
		for(k=0;k<16;k++) begin
			{A,B,C,D} = k;#10;
		end
		$display("Test complete");
	end
endmodule

Lab 5/Q1/Q1_tb.vcd
$date
	Wed Aug 28 10:32:29 2024
$end
$version
	Icarus Verilog
$end
$timescale
	1ns
$end
$scope module Q1_tb $end
$var wire 1 ! s1 $end
$var wire 1 " s0 $end
$var wire 4 # i [3:0] $end
$var wire 1 $ f $end
$var reg 1 % A $end
$var reg 1 & B $end
$var reg 1 ' C $end
$var reg 1 ( D $end
$var integer 32 ) k [31:0] $end
$scope module func $end
$var wire 1 % A $end
$var wire 1 & B $end
$var wire 1 ' C $end
$var wire 1 ( D $end
$var wire 1 " s0 $end
$var wire 1 ! s1 $end
$var reg 1 $ f $end
$var reg 4 * i [3:0] $end
$upscope $end
$upscope $end
$enddefinitions $end
#0
$dumpvars
b1011 *
b0 )
0(
0'
0&
0%
1$
b1011 #
0"
0!
$end
#10
b101 #
b101 *
1(
b1 )
#20
b1011 #
b1011 *
1'
0(
b10 )
#30
0$
b0 #
b0 *
1(
b11 )
#40
1$
b1011 #
b1011 *
1"
1&
0'
0(
b100 )
#50
0$
b101 #
b101 *
1(
b101 )
#60
1$
b1011 #
b1011 *
1'
0(
b110 )
#70
0$
b0 #
b0 *
1(
b111 )
#80
b1011 #
b1011 *
1!
1%
0"
0&
0'
0(
b1000 )
#90
1$
b101 #
b101 *
1(
b1001 )
#100
0$
b1011 #
b1011 *
1'
0(
b1010 )
#110
b0 #
b0 *
1(
b1011 )
#120
1$
b1011 #
b1011 *
1"
1&
0'
0(
b1100 )
#130
0$
b101 #
b101 *
1(
b1101 )
#140
1$
b1011 #
b1011 *
1'
0(
b1110 )
#150
0$
b0 #
b0 *
1(
b1111 )
#160
b10000 )
